django_skd_smoke-0.1.dist-info/DESCRIPTION.rst
django_skd_smoke-0.1.dist-info/METADATA
django_skd_smoke-0.1.dist-info/RECORD
django_skd_smoke-0.1.dist-info/WHEEL
django_skd_smoke-0.1.dist-info/metadata.json
django_skd_smoke-0.1.dist-info/top_level.txt
skd_smoke/__init__.py
